CHANGELOG.rst
LICENSE.txt
MANIFEST.in
README.rst
TODO.txt
VERSION.txt
setup.cfg
setup.py
svnpublish/__init__.py
svnpublish/api.py
svnpublish/async.py
svnpublish/cli.py
svnpublish/framework.py
svnpublish/i18n.py
svnpublish/reposchange.py
svnpublish/revinfo.py
svnpublish/subversion.py
svnpublish/test_framework.py
svnpublish/test_helper.py
svnpublish/test_revinfo.py
svnpublish/test_subversion.py
svnpublish.egg-info/PKG-INFO
svnpublish.egg-info/SOURCES.txt
svnpublish.egg-info/dependency_links.txt
svnpublish.egg-info/entry_points.txt
svnpublish.egg-info/requires.txt
svnpublish.egg-info/top_level.txt
svnpublish.egg-info/zip-safe
svnpublish/engine/__init__.py
svnpublish/engine/echo.py
svnpublish/engine/email.py
svnpublish/engine/export.py
svnpublish/engine/fingerprint.py
svnpublish/engine/genshi_compile.py
svnpublish/engine/genshic.py
svnpublish/engine/restsync.py
svnpublish/engine/rss.py
svnpublish/engine/shell.py
svnpublish/engine/test_echo.py
svnpublish/engine/test_email.py
svnpublish/engine/test_export.py
svnpublish/engine/test_fingerprint.py
svnpublish/engine/test_genshic.py
svnpublish/engine/test_restsync.py
svnpublish/engine/test_rss.py
svnpublish/engine/test_shell.py
svnpublish/res/options.yaml
svnpublish/res/engine-email/diff.mako
svnpublish/res/engine-email/truncated.css
svnpublish/res/engine-email/truncated.mako
svnpublish/res/engine-rss/feed.mako
svnpublish/res/engine-rss/item.mako
svnpublish/res/framework/error.mako
svnpublish/test/repos.tgz
svnpublish/test/repos/README.txt
svnpublish/test/repos/format
svnpublish/test/repos.svn/app/README.txt
svnpublish/test/repos.svn/app/__init__.py
svnpublish/test/repos.svn/app/nonewline.py
svnpublish/test/repos.svn/app/program.py
svnpublish/test/repos.svn/content/textfile.txt
svnpublish/test/repos.svn/content/directory/content.html.gst
svnpublish/test/repos.svn/content/directory/textfile.txt
svnpublish/test/repos.svn/property/file1.txt
svnpublish/test/repos.svn/property/file2.txt
svnpublish/test/repos.svn/property/file3.txt
svnpublish/test/repos/conf/authz
svnpublish/test/repos/conf/passwd
svnpublish/test/repos/conf/svnserve.conf
svnpublish/test/repos/db/current
svnpublish/test/repos/db/format
svnpublish/test/repos/db/fs-type
