Metadata-Version: 1.1
Name: svnpublish
Version: 2.12
Summary: Enables powerful automation from a subversion repository.
Home-page: http://github.com/metagriffin/svnpublish
Author: metagriffin
Author-email: mg.pypi@uberdev.org
License: GPLv3+
Keywords: svn subversion publish automation actions deploy test testing
Platform: any
Classifier: Development Status :: 5 - Production/Stable
Classifier: Environment :: Console
Classifier: Intended Audience :: Developers
Classifier: Intended Audience :: Information Technology
Classifier: Intended Audience :: System Administrators
Classifier: Natural Language :: English
Classifier: Operating System :: OS Independent
Classifier: Programming Language :: Python
Classifier: Topic :: Internet :: WWW/HTTP :: Site Management
Classifier: Topic :: Other/Nonlisted Topic
Classifier: Topic :: Software Development
Classifier: Topic :: Software Development :: Libraries :: Python Modules
Classifier: Topic :: Software Development :: Version Control
Classifier: Topic :: Utilities
Classifier: License :: OSI Approved :: GNU General Public License v3 or later (GPLv3+)
